AUTHORS
ChangeLog
LICENSE.txt
README.rst
codestyle.toml
requirements.txt
setup.cfg
setup.py
test.py
ImoT_tools.egg-info/PKG-INFO
ImoT_tools.egg-info/SOURCES.txt
ImoT_tools.egg-info/dependency_links.txt
ImoT_tools.egg-info/not-zip-safe
ImoT_tools.egg-info/pbr.json
ImoT_tools.egg-info/requires.txt
ImoT_tools.egg-info/top_level.txt
doc/conf.py
doc/index.rst
doc/api/imot_tools.io.fits.rst
doc/api/imot_tools.io.plot.rst
doc/api/imot_tools.io.rst
doc/api/imot_tools.io.s2image.rst
doc/api/imot_tools.math.func.rst
doc/api/imot_tools.math.linalg.rst
doc/api/imot_tools.math.rst
doc/api/imot_tools.math.special.rst
doc/api/imot_tools.math.sphere.grid.rst
doc/api/imot_tools.math.sphere.interpolate.rst
doc/api/imot_tools.math.sphere.rst
doc/api/imot_tools.math.sphere.transform.rst
doc/api/imot_tools.math.stat.rst
doc/api/imot_tools.phased_array.rst
doc/api/imot_tools.util.argcheck.rst
doc/api/imot_tools.util.array.rst
doc/api/imot_tools.util.rst
doc/api/index.rst
doc/api/_img/cmap_example.png
doc/api/_img/colorbar_example.png
doc/api/_img/sph_dirichlet_example.png
doc/api/_img/sphericalimage_aeqd_example.png
doc/api/_img/sphericalimage_gnom_example.png
doc/api/_img/sphericalimage_lcc_example.png
doc/general/index.rst
doc/general/install.rst
doc/notes/func_interpolation_OL_zonal.rst
doc/notes/index.rst
imot_tools/__init__.py
imot_tools/data/io/imot_tools.mplstyle
imot_tools/data/io/colormap/algue.csv
imot_tools/data/io/colormap/aqua.csv
imot_tools/data/io/colormap/fire.csv
imot_tools/data/io/colormap/jet_alt.csv
imot_tools/data/io/colormap/lava.csv
imot_tools/data/io/colormap/lightbulb.csv
imot_tools/data/math/special/ive_threshold.csv
imot_tools/data/math/special/jv_series_threshold.csv
imot_tools/data/math/special/jv_threshold.csv
imot_tools/data/math/special/spherical_jn_series_threshold.csv
imot_tools/data/math/special/spherical_jn_threshold.csv
imot_tools/io/__init__.py
imot_tools/io/fits.py
imot_tools/io/plot.py
imot_tools/io/s2image.py
imot_tools/math/__init__.py
imot_tools/math/func.py
imot_tools/math/linalg.py
imot_tools/math/special.py
imot_tools/math/stat.py
imot_tools/math/sphere/__init__.py
imot_tools/math/sphere/grid.py
imot_tools/math/sphere/interpolate.py
imot_tools/math/sphere/transform.py
