Metadata-Version: 2.1
Name: ImoT-tools
Version: 1.2.0
Summary: Collection of useful tools common to ImagingOfThings projects.
Home-page: https://github.com/imagingofthings/ImoT_tools
Download-URL: https://github.com/imagingofthings/ImoT_tools
Author: Sepand KASHANI
Author-email: kashani.sepand@gmail.com
License: BSD
Classifier: Development Status :: 5 - Production/Stable
Classifier: Intended Audience :: Science/Research
Classifier: License :: OSI Approved :: BSD License
Classifier: Programming Language :: Python :: 3
Classifier: Programming Language :: Python :: Implementation :: CPython
Classifier: Topic :: Scientific/Engineering
Requires-Python: >=3.6
License-File: LICENSE.txt
License-File: AUTHORS
